vk_audio/secondDecoderFunc.cp38-win32.pyd
module1991-2.0.dist-info/METADATA
module1991-2.0.dist-info/WHEEL
module1991-2.0.dist-info/top_level.txt
module1991-2.0.dist-info/RECORD
