Metadata-Version: 2.1
Name: module1991
Version: 2.0
Summary: This is a demo package
Home-page: UNKNOWN
Author: UNKNOWN
Author-email: UNKNOWN
License: UNKNOWN
Platform: UNKNOWN
